Taowa_skin/Skin列表.py
Taowa_skin/__init__.py
Taowa_skin/skin.py
Taowa_skin/she/SkinH_EL.dll
Taowa_skin/she/皮肤_360safe
Taowa_skin/she/皮肤_Adamant
Taowa_skin/she/皮肤_Areo
Taowa_skin/she/皮肤_Asus
Taowa_skin/she/皮肤_Black
Taowa_skin/she/皮肤_Black04
Taowa_skin/she/皮肤_Dogmax
Taowa_skin/she/皮肤_ENJOY
Taowa_skin/she/皮肤_FlatUI
Taowa_skin/she/皮肤_IllumeCG
Taowa_skin/she/皮肤_Itunes
Taowa_skin/she/皮肤_Longhorn
Taowa_skin/she/皮肤_MAC
Taowa_skin/she/皮肤_MSN
Taowa_skin/she/皮肤_Pink漂亮
Taowa_skin/she/皮肤_QQ2008
Taowa_skin/she/皮肤_QQ2009
Taowa_skin/she/皮肤_QQ2009黑色
Taowa_skin/she/皮肤_QQ2011
Taowa_skin/she/皮肤_QQ2015
Taowa_skin/she/皮肤_QQGame
Taowa_skin/she/皮肤_QQMusic3
Taowa_skin/she/皮肤_QQ影音
Taowa_skin/she/皮肤_QQ浏览器
Taowa_skin/she/皮肤_QQ金属雅灰
Taowa_skin/she/皮肤_QQ音乐
Taowa_skin/she/皮肤_SHWIN
Taowa_skin/she/皮肤_ShanMeng窄版
Taowa_skin/she/皮肤_Storm
Taowa_skin/she/皮肤_TIM
Taowa_skin/she/皮肤_TIM_无框
Taowa_skin/she/皮肤_VX
Taowa_skin/she/皮肤_Vista绿
Taowa_skin/she/皮肤_WIN10修复
Taowa_skin/she/皮肤_WhiteFire
Taowa_skin/she/皮肤_Win7
Taowa_skin/she/皮肤_Win8SHE
Taowa_skin/she/皮肤_Xenes
Taowa_skin/she/皮肤_compact
Taowa_skin/she/皮肤_photo
Taowa_skin/she/皮肤_photo2
Taowa_skin/she/皮肤_studio
Taowa_skin/she/皮肤_svip
Taowa_skin/she/皮肤_xmp
Taowa_skin/she/皮肤_中国风
Taowa_skin/she/皮肤_仿爱思助手
Taowa_skin/she/皮肤_可爱蓝
Taowa_skin/she/皮肤_彗星小助手深蓝色
Taowa_skin/she/皮肤_彩虹
Taowa_skin/she/皮肤_显眼蓝
Taowa_skin/she/皮肤_浅黑
Taowa_skin/she/皮肤_清新蓝
Taowa_skin/she/皮肤_清新蓝白
Taowa_skin/she/皮肤_清新蓝调
Taowa_skin/she/皮肤_清新青
Taowa_skin/she/皮肤_清爽灰白
Taowa_skin/she/皮肤_清爽炫蓝
Taowa_skin/she/皮肤_灰蓝
Taowa_skin/she/皮肤_积木
Taowa_skin/she/皮肤_简洁黑红
Taowa_skin/she/皮肤_简约清爽
Taowa_skin/she/皮肤_简约灰白
Taowa_skin/she/皮肤_简约灰绿
Taowa_skin/she/皮肤_简约白
Taowa_skin/she/皮肤_简约蓝
Taowa_skin/she/皮肤_简约蓝灰
Taowa_skin/she/皮肤_简约青
Taowa_skin/she/皮肤_简约青蓝
Taowa_skin/she/皮肤_简约黑
Taowa_skin/she/皮肤_粉红主题
Taowa_skin/she/皮肤_精易编程助手
Taowa_skin/she/皮肤_紫色浅粉
Taowa_skin/she/皮肤_红蓝渐变
Taowa_skin/she/皮肤_纯净皮肤
Taowa_skin/she/皮肤_绿调
Taowa_skin/she/皮肤_腾讯
Taowa_skin/she/皮肤_自绘蓝
Taowa_skin/she/皮肤_蓝色电脑管家
Taowa_skin/she/皮肤_蓝调
Taowa_skin/she/皮肤_记忆蓝
Taowa_skin-1.0.3.dist-info/METADATA
Taowa_skin-1.0.3.dist-info/WHEEL
Taowa_skin-1.0.3.dist-info/top_level.txt
Taowa_skin-1.0.3.dist-info/RECORD
