Metadata-Version: 2.1
Name: Taowa_skin
Version: 1.0.3
Summary: Skin皮肤模块
Author: 
Author-email: 
Classifier: Programming Language :: Python :: 3
Classifier: License :: OSI Approved :: MIT License
Classifier: Operating System :: OS Independent
Requires-Python: >=3.6
